agentsdk/__init__.py
agentsdk/agent.py
agentsdk/aws.py
agentsdk/cli.py
agentsdk/orchestration.py
agentsdk/state.py
agentsdk/tool_subsystem.py
agentsdk/tools/FileSystemTool.py
agentsdk/tools/ShellTool.py
agentsdk/tools/WebSearchTool.py
agentsdk_ayush-0.1.0.dist-info/licenses/LICENSE
agentsdk_ayush-0.1.0.dist-info/METADATA
agentsdk_ayush-0.1.0.dist-info/WHEEL
agentsdk_ayush-0.1.0.dist-info/entry_points.txt
agentsdk_ayush-0.1.0.dist-info/top_level.txt
agentsdk_ayush-0.1.0.dist-info/RECORD
